cbmc_starter_kit/__init__.py
cbmc_starter_kit/arguments.py
cbmc_starter_kit/ctagst.py
cbmc_starter_kit/migrate_license.py
cbmc_starter_kit/repository.py
cbmc_starter_kit/setup.py
cbmc_starter_kit/setup_ci.py
cbmc_starter_kit/setup_proof.py
cbmc_starter_kit/update.py
cbmc_starter_kit/util.py
cbmc_starter_kit/version.py
cbmc_starter_kit/etc/bash_completion.d/cbmc-starter-kit.sh
cbmc_starter_kit/template-for-ci-workflow/proof_ci.yaml
cbmc_starter_kit/template-for-ci-workflow/proof_ci_resources/config.yaml
cbmc_starter_kit/template-for-proof/FUNCTION_harness.c
cbmc_starter_kit/template-for-proof/Makefile
cbmc_starter_kit/template-for-proof/README.md
cbmc_starter_kit/template-for-proof/cbmc-proof.txt
cbmc_starter_kit/template-for-proof/cbmc-viewer.json
cbmc_starter_kit/template-for-repository/.gitignore
cbmc_starter_kit/template-for-repository/include/README.md
cbmc_starter_kit/template-for-repository/negative_tests/README.md
cbmc_starter_kit/template-for-repository/negative_tests/assert/Makefile
cbmc_starter_kit/template-for-repository/negative_tests/assert/assert_harness.c
cbmc_starter_kit/template-for-repository/negative_tests/bounds_check/Makefile
cbmc_starter_kit/template-for-repository/negative_tests/bounds_check/bounds_check_harness.c
cbmc_starter_kit/template-for-repository/negative_tests/conversion_check/Makefile
cbmc_starter_kit/template-for-repository/negative_tests/conversion_check/conversion_check_harness.c
cbmc_starter_kit/template-for-repository/negative_tests/div_by_zero_check/Makefile
cbmc_starter_kit/template-for-repository/negative_tests/div_by_zero_check/div_by_zero_check_harness.c
cbmc_starter_kit/template-for-repository/negative_tests/float_overflow_check/Makefile
cbmc_starter_kit/template-for-repository/negative_tests/float_overflow_check/float_overflow_check_harness.c
cbmc_starter_kit/template-for-repository/negative_tests/float_underflow_check/Makefile
cbmc_starter_kit-2.10.dist-info/LICENSE
cbmc_starter_kit-2.10.dist-info/METADATA
cbmc_starter_kit-2.10.dist-info/NOTICE
cbmc_starter_kit-2.10.dist-info/WHEEL
cbmc_starter_kit-2.10.dist-info/entry_points.txt
cbmc_starter_kit-2.10.dist-info/top_level.txt
cbmc_starter_kit-2.10.dist-info/RECORD
