Metadata-Version: 2.1
Name: cbmc-starter-kit
Version: 2.10
Summary: CBMC starter kit makes it easy to add CBMC verification to a software project
Home-page: https://github.com/model-checking/cbmc-starter-kit
Author: Mark R. Tuttle
Author-email: mrtuttle@amazon.com
License: Apache License 2.0
Classifier: Programming Language :: Python :: 3
Classifier: License :: OSI Approved :: Apache Software License
Classifier: Operating System :: OS Independent
Requires-Python: >=3.8
License-File: LICENSE
License-File: NOTICE
Requires-Dist: gitpython
Requires-Dist: setuptools
